geomodel_optimizer/__init__.py
geomodel_optimizer/optimizer.py
geomodel_optimizer/utils.py
geomodel_optimizer/waiwerarun.py
geomodel_optimizer-0.5.1.dist-info/licenses/LICENSE.txt
geomodel_optimizer-0.5.1.dist-info/METADATA
geomodel_optimizer-0.5.1.dist-info/WHEEL
geomodel_optimizer-0.5.1.dist-info/top_level.txt
geomodel_optimizer-0.5.1.dist-info/RECORD
