Metadata-Version: 2.4
Name: geomodel_optimizer
Version: 0.5.1
Summary: Location optimizer for Waiwera simulations
Home-page: https://github.com/ISOR-Geothermal/GeoModel-Optimizer
Author: Rögnvaldur L. Magnússon
Author-email: rm@isor.is
Classifier: Programming Language :: Python :: 3
Classifier: License :: OSI Approved :: MIT License
Classifier: Operating System :: OS Independent
Classifier: Intended Audience :: Science/Research
Classifier: Environment :: Console
Classifier: Topic :: Scientific/Engineering :: Hydrology
Requires-Python: >=3.10
License-File: LICENSE.txt
Requires-Dist: pandas
Requires-Dist: layermesh
Requires-Dist: pywaiwera
Requires-Dist: tqdm
Dynamic: author
Dynamic: author-email
Dynamic: classifier
Dynamic: description
Dynamic: description-content-type
Dynamic: home-page
Dynamic: license-file
Dynamic: requires-dist
Dynamic: requires-python
Dynamic: summary
